LICENSE.txt
MANIFEST.in
README.md
requirements.txt
setup.py
django_keen.egg-info/PKG-INFO
django_keen.egg-info/SOURCES.txt
django_keen.egg-info/dependency_links.txt
django_keen.egg-info/requires.txt
django_keen.egg-info/top_level.txt
dkeen/__init__.py
dkeen/client.py
dkeen/tasks.py