Metadata-Version: 1.0
Name: django-keen
Version: 0.1.3
Summary: Simple wrapper for django around the official keen.io client
Home-page: http://pypi.python.org/pypi/django-keen/
Author: Jannis Gebauer
Author-email: ja.geb@pricemesh.io
License: LICENSE.txt
Platform: UNKNOWN
